predmarket/__init__.py
predmarket/kalshi/__init__.py
predmarket/kalshi/rest.py
predmarket/model/__init__.py
predmarket/model/rest/__init__.py
predmarket/model/rest/contract.py
predmarket/model/rest/exchange.py
predmarket/model/rest/price.py
predmarket/model/rest/question.py
predmarket/model/rest/response.py
predmarket/model/ws/__init__.py
predmarket/model/ws/exchange.py
predmarket/model/ws/normalize.py
predmarket/polymarket/__init__.py
predmarket/polymarket/rest.py
predmarket/polymarket/ws.py
predmarket-0.1.0.dist-info/METADATA
predmarket-0.1.0.dist-info/WHEEL
predmarket-0.1.0.dist-info/top_level.txt
predmarket-0.1.0.dist-info/RECORD
