Metadata-Version: 2.4
Name: predmarket
Version: 0.1.0
Summary: Unified data API for Kalshi and Polymarket. Core schema + clean SDk.
Requires-Python: >=3.12
Requires-Dist: httpx>=0.28.1
Requires-Dist: pydantic>=2.11.10
Requires-Dist: structlog>=25.4.0
Requires-Dist: websockets>=15.0.1
Requires-Dist: yarl>=1.22.0
